pentachoron/__init__.py
pentachoron/test.py
pentachoron/qubits/__init__.py
pentachoron/qubits/algorithms.py
pentachoron/qubits/circuit.py
pentachoron/qubits/gates.py
pentachoron/qubits/quantum_language.py
pentachoron/qubits/qubit.py
pentachoron/qubits/simulator.py
pentachoron/qutrits/Qutrit.py
pentachoron/qutrits/__init__.py
pentachoron/qutrits/circuit_qutrit.py
pentachoron/qutrits/gates_qutrit.py
pentachoron/qutrits/quantum_language_qutrit.py
pentachoron/qutrits/simulator_qutrit.py
pentachoron-0.2.dist-info/METADATA
pentachoron-0.2.dist-info/WHEEL
pentachoron-0.2.dist-info/top_level.txt
pentachoron-0.2.dist-info/RECORD
